{
  "name": "The LEGO Batman Movie",
  "Rating:": "PG (Rude Humor and Some Action)",
  "Genre:": "Kids & family, \n                        \n                        Adventure, \n                        \n                        Action, \n                        \n                        Animation, \n                        \n                        Comedy",
  "Original Language:": "English",
  "Director:": "Chris McKay",
  "Producer:": "Dan Lin, \n                            \n                        \n                            \n                                Phil Lord, \n                            \n                        \n                            \n                                Chris Miller, \n                            \n                        \n                            \n                                Roy Lee",
  "Writer:": "Seth Grahame-Smith, \n                            \n                        \n                            \n                                Chris McKenna, \n                            \n                        \n                            \n                                Erik Sommers, \n                            \n                        \n                            \n                                Jared Stern, \n                            \n                        \n                            \n                                John Whittington",
  "Release Date (Theaters):": "Feb 10, 2017\n\u00a0wide",
  "Release Date (Streaming):": "Jun 13, 2017",
  "Box Office (Gross USA):": "$175.7M",
  "Runtime:": "1h 46m",
  "Distributor:": "Warner Bros. Pictures",
  "Sound Mix:": "Dolby Atmos, Dolby Digital, SDDS, Datasat",
  "Aspect Ratio:": "Scope (2.35:1)",
  "View the collection:": "Batman"
}